pymoutility/__init__.py
pymoutility/decorators.py
pymoutility/notebooks/Examples.ipynb
pymoutility/src/__init__.py
pymoutility/src/debugger.py
pymoutility/src/logger_setup.py
pymoutility-0.1.1.dist-info/LICENSE
pymoutility-0.1.1.dist-info/METADATA
pymoutility-0.1.1.dist-info/WHEEL
pymoutility-0.1.1.dist-info/RECORD
