Metadata-Version: 2.1
Name: pymoutility
Version: 0.1.1
Summary: A handy collection of helper functions, decorators, and utilities designed to streamline and simplify your Python 🐍 development experience. It provides powerful tools to make your code cleaner, more readable, and easier to debug.
License: ./LICENSE
Author: JasGujral
Author-email: jasmeet.gujral@mostacktechnology.com
Requires-Python: >=3.10,<4.0
Classifier: License :: Other/Proprietary License
Classifier: Programming Language :: Python :: 3
Classifier: Programming Language :: Python :: 3.10
Classifier: Programming Language :: Python :: 3.11
Requires-Dist: jupyter (>=1.0.0,<2.0.0)
